SpiderReverser_Modules/ApiRequestUtils.py
SpiderReverser_Modules/FileHandleUtils.py
SpiderReverser_Modules/__init__.py
SpiderReverser_Modules-1.0.8.dist-info/LICENSE
SpiderReverser_Modules-1.0.8.dist-info/METADATA
SpiderReverser_Modules-1.0.8.dist-info/WHEEL
SpiderReverser_Modules-1.0.8.dist-info/top_level.txt
SpiderReverser_Modules-1.0.8.dist-info/RECORD
